[
  {
    "type": "function",
    "name": "providers",
    "inputs": [
      {
        "name": "",
        "type": "address",
        "internalType": "address"
      }
    ],
    "outputs": [
      {
        "name": "weightRoot",
        "type": "bytes32",
        "internalType": "bytes32"
      },
      {
        "name": "stake",
        "type": "uint256",
        "internalType": "uint256"
      },
      {
        "name": "active",
        "type": "bool",
        "internalType": "bool"
      }
    ],
    "stateMutability": "view"
  },
  {
    "type": "function",
    "name": "register",
    "inputs": [
      {
        "name": "weightRoot",
        "type": "bytes32",
        "internalType": "bytes32"
      }
    ],
    "outputs": [],
    "stateMutability": "payable"
  },
  {
    "type": "event",
    "name": "ProviderRegistered",
    "inputs": [
      {
        "name": "provider",
        "type": "address",
        "indexed": true,
        "internalType": "address"
      },
      {
        "name": "weightRoot",
        "type": "bytes32",
        "indexed": true,
        "internalType": "bytes32"
      },
      {
        "name": "stake",
        "type": "uint256",
        "indexed": false,
        "internalType": "uint256"
      }
    ],
    "anonymous": false
  }
]
